<?xml version='1.0' encoding='UTF-8'?>
<overlaydata>
	<markercategory name="griffon_flying" displayname="Griffon Flying">
		<markercategory name="stunts" displayname="Stunts">
			<markercategory name="easy" displayname="1 Star - Easy">
				<markercategory name="kryta" displayname="Kryta">
					<markercategory name="divinitys_reach" displayname="Divinity's Reach">
						<markercategory name="worship_of_g" displayname="Worship of G">
						</markercategory>
					</markercategory>
				</markercategory>
			</markercategory>
		</markercategory>
	</markercategory>
	<pois>		
		<!--Divinity's Reach - Worship of G - Creator: Mozzy-->
		<poi mapid="18" xpos="43.0493" ypos="199.694" zpos="224.974" type="griffon_flying.stunts.easy.kryta.start" guid="IeRHzdqX2UG9oPcQF8DcuQ=="/>
		<poi mapid="18" xpos="37.3234" ypos="199.091" zpos="223.34" type="griffon_flying.stunts.easy.kryta.springer" guid="vaqtoUElKEuox8qBpaLVMA=="/>
		<poi mapid="18" xpos="35.8118" ypos="223.046" zpos="223.061" type="griffon_flying.stunts.easy.kryta.griffon" guid="JYLuqmKSFECt7OZjFmxOFQ=="/>
		<poi mapid="18" xpos="36.0281" ypos="199.649" zpos="220.92" type="griffon_flying.stunts.easy.kryta.finish" guid="6JVrV4mc2EO8lFGMY7Ffqw=="/>
		<trail traildata="Data\Trails\stunts\1star\stunts_1star_kryta_divinitysreach_worshipofg.trl" type="griffon_flying.stunts.easy.kryta.divinitys_reach.worship_of_g" guid="EN/Sd7WZdk2A81Pr1fT5GQ==" alpha="0.9" fadenear="4000" fadefar="5000" color="74c580" animspeed="0.2" texture="Data/Markers/feather.png"/>
	</pois>
</overlaydata>